bunq.py
bunq-0.0.2.dist-info/DESCRIPTION.rst
bunq-0.0.2.dist-info/METADATA
bunq-0.0.2.dist-info/RECORD
bunq-0.0.2.dist-info/WHEEL
bunq-0.0.2.dist-info/metadata.json
bunq-0.0.2.dist-info/top_level.txt
