Metadata-Version: 2.0
Name: bunq
Version: 0.0.2
Summary: Simple wrapper around the bunq API
Home-page: https://github.com/madeddie/python-bunq
Author: Edwin Hermans
Author-email: edwin@madtech.cx
License: MIT
Platform: UNKNOWN
Requires-Dist: cryptography
Requires-Dist: requests
